PyTouchBar/Haptic.py
PyTouchBar/TouchBar.py
PyTouchBar/__init__.py
PyTouchBar/action.py
PyTouchBar/constants.py
PyTouchBar/exceptions.py
PyTouchBar/items.py
PyTouchBar/tests.py
PyTouchBar/utilities.py
PyTouchBar-0.2.1.dist-info/LICENSE
PyTouchBar-0.2.1.dist-info/METADATA
PyTouchBar-0.2.1.dist-info/WHEEL
PyTouchBar-0.2.1.dist-info/top_level.txt
PyTouchBar-0.2.1.dist-info/RECORD
