Metadata-Version: 2.1
Name: PyTouchBar
Version: 0.2.1
Summary: Use MacBook Pro's TouchBar in Python
Home-page: https://github.com/Maxmad68/PyTouchBar
Author: Maxmad68
Author-email: maxime@madrau.fr
Classifier: Programming Language :: Python :: 3
Classifier: License :: OSI Approved :: MIT License
Classifier: Operating System :: OS Independent
Requires-Python: >=3.2
License-File: LICENSE
